{
  "schemaVersion": "frameangel_player_package_profile_v1",
  "productId": "modern_tv_player_free",
  "displayName": "Modern TV Player",
  "editionProfilePath": "products/vam/assets/player/config/edition_profiles/free.json",
  "surfaceProfilePath": "products/vam/assets/player/config/surface_profiles/modern_tv_player.json",
  "packageIdentity": {
    "creatorName": "FrameAngel",
    "packageName": "ModernTVPlayer",
    "licenseType": "CC BY-NC-ND"
  },
  "listing": {
    "description": "FrameAngel Modern TV Player free edition.",
    "credits": "",
    "instructions": "",
    "promotionalLink": ""
  },
  "buildDefaults": {
    "packageChannel": "release",
    "includeScene": false,
    "includeDemoMedia": false,
    "includeShellFamily": false
  }
}
